LICENSE.md
MANIFEST.in
README.md
setup.py
admin_volt/__init__.py
admin_volt/admin.py
admin_volt/apps.py
admin_volt/forms.py
admin_volt/urls.py
admin_volt/utils.py
admin_volt/views.py
admin_volt/migrations/__init__.py
admin_volt/static/.gitkeep
admin_volt/static/gulpfile.js
admin_volt/static/assets/img/marker.svg
admin_volt/static/assets/img/mockup-calendar-presentation.png
admin_volt/static/assets/img/mockup-kanban-presentation.png
admin_volt/static/assets/img/mockup-map-presentation.png
admin_volt/static/assets/img/mockup-presentation.png
admin_volt/static/assets/img/paypal-logo.svg
admin_volt/static/assets/img/profile-cover.jpg
admin_volt/static/assets/img/themesberg-logo-alt.svg
admin_volt/static/assets/img/themesberg-mockup.jpg
admin_volt/static/assets/img/themesberg.svg
admin_volt/static/assets/img/brand/dark.svg
admin_volt/static/assets/img/brand/light.svg
admin_volt/static/assets/img/favicon/android-chrome-192x192.png
admin_volt/static/assets/img/favicon/android-chrome-512x512.png
admin_volt/static/assets/img/favicon/apple-touch-icon.png
admin_volt/static/assets/img/favicon/browserconfig.xml
admin_volt/static/assets/img/favicon/favicon-16x16.png
admin_volt/static/assets/img/favicon/favicon-32x32.png
admin_volt/static/assets/img/favicon/favicon.ico
admin_volt/static/assets/img/favicon/manifest.json
admin_volt/static/assets/img/favicon/mstile-150x150.png
admin_volt/static/assets/img/favicon/safari-pinned-tab.svg
admin_volt/static/assets/img/favicon/site.webmanifest
admin_volt/static/assets/img/flags/aland-islands.svg
admin_volt/static/assets/img/flags/albania.svg
admin_volt/static/assets/img/flags/algeria.svg
admin_volt/static/assets/img/flags/american-samoa.svg
admin_volt/static/assets/img/flags/anguilla.svg
admin_volt/static/assets/img/flags/argentina.svg
admin_volt/static/assets/img/flags/armenia.svg
admin_volt/static/assets/img/flags/australia.svg
admin_volt/static/assets/img/flags/austria.svg
admin_volt/static/assets/img/flags/azerbaijan.svg
django_admin_volt.egg-info/PKG-INFO
django_admin_volt.egg-info/SOURCES.txt
django_admin_volt.egg-info/dependency_links.txt
django_admin_volt.egg-info/not-zip-safe
django_admin_volt.egg-info/top_level.txt
